[
   {
      "firstName":"Chlo",
      "lastName":"Petticrow",
      "licenceNo":"39-180-2308",
      "ticketCount":"44"
   },
   {
      "firstName":"Felice",
      "lastName":"Burberye",
      "licenceNo":"89-450-4072",
      "ticketCount":"4"
   },
   {
      "firstName":"Rozina",
      "lastName":"Dorey",
      "licenceNo":"73-133-0391",
      "ticketCount":"185"
   },
   {
      "firstName":"Helaina",
      "lastName":"Tesimon",
      "licenceNo":"22-981-2768",
      "ticketCount":"3"
   },
   {
      "firstName":"Chip",
      "lastName":"Gauden",
      "licenceNo":"55-522-7867",
      "ticketCount":"2296"
   },
   {
      "firstName":"Sigismond",
      "lastName":"Ewbach",
      "licenceNo":"25-247-7083",
      "ticketCount":"32418"
   },
   {
      "firstName":"Bili",
      "lastName":"Pandie",
      "licenceNo":"95-616-5537",
      "ticketCount":"8"
   },
   {
      "firstName":"Gilli",
      "lastName":"Limon",
      "licenceNo":"58-241-2419",
      "ticketCount":"7489"
   },
   {
      "firstName":"Ramsey",
      "lastName":"Querrard",
      "licenceNo":"05-221-6219",
      "ticketCount":"4382"
   },
   {
      "firstName":"Dorris",
      "lastName":"Yonnie",
      "licenceNo":"03-484-9736",
      "ticketCount":"5"
   },
   {
      "firstName":"Patrick",
      "lastName":"Whiffin",
      "licenceNo":"41-944-9411",
      "ticketCount":"40"
   },
   {
      "firstName":"Wendye",
      "lastName":"Jendrach",
      "licenceNo":"91-666-6191",
      "ticketCount":"125"
   },
   {
      "firstName":"Dniren",
      "lastName":"Kynsey",
      "licenceNo":"35-038-9678",
      "ticketCount":"31875"
   },
   {
      "firstName":"Emlyn",
      "lastName":"Batty",
      "licenceNo":"41-568-3261",
      "ticketCount":"7"
   },
   {
      "firstName":"Maynord",
      "lastName":"Sutton",
      "licenceNo":"11-697-6794",
      "ticketCount":"3"
   },
   {
      "firstName":"Essa",
      "lastName":"Kinzel",
      "licenceNo":"02-188-8011",
      "ticketCount":"5"
   },
   {
      "firstName":"Aigneis",
      "lastName":"Huddy",
      "licenceNo":"68-380-8628",
      "ticketCount":"94807"
   },
   {
      "firstName":"Myer",
      "lastName":"Greenhough",
      "licenceNo":"32-121-5364",
      "ticketCount":"46"
   },
   {
      "firstName":"Marcello",
      "lastName":"Bolderoe",
      "licenceNo":"93-702-4723",
      "ticketCount":"14"
   },
   {
      "firstName":"Gilburt",
      "lastName":"O'Fearguise",
      "licenceNo":"87-445-5602",
      "ticketCount":"62"
   }
]
